silentpushcli-1.3.0.dist-info/licenses/LICENSE.txt
sp/__init__.py
sp/main.py
sp/settings.py
sp/commands/__init__.py
sp/commands/answer.py
sp/commands/enrich.py
sp/commands/query.py
sp/commands/score.py
sp/commands/search.py
sp/commands/spql.py
sp/commands/threatcheck.py
sp/commands/base/BaseCmdApp.py
sp/commands/base/BaseCommand.py
sp/commands/base/BaseCommandSet.py
sp/commands/base/__init__.py
sp/commands/base/enrich.py
sp/commands/base/padns.py
sp/commands/base/spql.py
sp/commands/base/threatcheck.py
sp/common/__init__.py
sp/common/parse_ioc.py
sp/common/utils.py
silentpushcli-1.3.0.dist-info/METADATA
silentpushcli-1.3.0.dist-info/WHEEL
silentpushcli-1.3.0.dist-info/entry_points.txt
silentpushcli-1.3.0.dist-info/top_level.txt
silentpushcli-1.3.0.dist-info/RECORD
