Metadata-Version: 2.4
Name: SilentPushCLI
Version: 1.3.0
Summary: Silent Push - Command Line Interface
Home-page: https://www.silentpush.com
Author: Jorgeley
Author-email: jorgeley@silentpush.com
License: https://www.silentpush.com/terms-of-use/
Keywords: cyber security,passive DNS
Classifier: Development Status :: 3 - Alpha
Classifier: Intended Audience :: Information Technology
Classifier: Intended Audience :: System Administrators
Classifier: Topic :: Internet :: Name Service (DNS)
Classifier: Topic :: Security
Classifier: Topic :: System :: Networking :: Firewalls
Classifier: Topic :: System :: System Shells
Classifier: Topic :: Terminals
Classifier: Programming Language :: Python :: 3
Classifier: Programming Language :: Python :: 3.9
Classifier: Programming Language :: Python :: 3.10
Classifier: Programming Language :: Python :: 3.11
Classifier: Programming Language :: Python :: 3 :: Only
Requires-Python: >=3.9
License-File: LICENSE.txt
Requires-Dist: wcwidth==0.2.13
Requires-Dist: pyperclip==1.8.2
Requires-Dist: validators>=0.20.0
Requires-Dist: tldextract>=3.1.2
Requires-Dist: gnureadline>=8.1.2; sys_platform != "win32" and sys_platform != "win_amd64"
Requires-Dist: pandas==2.0.0; sys_platform == "win32" or sys_platform == "win_amd64"
Requires-Dist: iniconfig>=1.1.1
Requires-Dist: cmd2==2.7.0
Requires-Dist: pandas>=2.0.3; sys_platform != "win32" and sys_platform != "win_amd64"
Requires-Dist: pyparsing==3.1.1
Requires-Dist: attrs>=22.2.0
Requires-Dist: requests>=2.27.1
Requires-Dist: python-dotenv>=0.20.0
Requires-Dist: pyreadline3>=3.4.1; sys_platform == "win32" or sys_platform == "win_amd64"
Requires-Dist: numpy==1.26.4; sys_platform == "win32" or sys_platform == "win_amd64"
Requires-Dist: urllib3==1.26.6
Requires-Dist: jsonschema==4.17.3
Requires-Dist: py==1.11.0
Requires-Dist: pluggy>=1.0.0
Requires-Dist: xdg==5.1.1
Dynamic: author
Dynamic: author-email
Dynamic: classifier
Dynamic: description
Dynamic: description-content-type
Dynamic: home-page
Dynamic: keywords
Dynamic: license
Dynamic: license-file
Dynamic: requires-dist
Dynamic: requires-python
Dynamic: summary
